dht20_sensor/__init__.py
dht20_sensor/sensor.py
dht20_sensor-0.0.2.dist-info/LICENSE
dht20_sensor-0.0.2.dist-info/METADATA
dht20_sensor-0.0.2.dist-info/WHEEL
dht20_sensor-0.0.2.dist-info/top_level.txt
dht20_sensor-0.0.2.dist-info/RECORD
