Metadata-Version: 2.1
Name: dht20_sensor
Version: 0.0.2
Summary: A minimal implementation for taking temperature and humidity readings with the DHT20 sensor
Author-email: Kieran Porter <kieranintehdas@gmail.com>
License: GPL-3.0-or-later
Project-URL: Homepage, https://github.com/KieraninTehdas/dht20-sensor
Classifier: Programming Language :: Python :: 3
Classifier: License :: OSI Approved :: GNU General Public License v3 or later (GPLv3+)
Classifier: Operating System :: OS Independent
Requires-Python: >=3.7
License-File: LICENSE
